library/__init__.py
library/myfunction.py
tests/__init__.py
tests/test_myfunction.py
ukritlibrary-0.1.3.dist-info/LICENSE.txt
ukritlibrary-0.1.3.dist-info/METADATA
ukritlibrary-0.1.3.dist-info/WHEEL
ukritlibrary-0.1.3.dist-info/top_level.txt
ukritlibrary-0.1.3.dist-info/RECORD
