Metadata-Version: 2.1
Name: ukritlibrary
Version: 0.1.3
Summary: My libraly From ukrit
Home-page: UNKNOWN
Author: Ukrit Fongsomboon
License: MIT
Platform: UNKNOWN
Requires-Python: >=3.8
